{
  "members": [
    {
      "name": "Creperia Mediodia",
      "address": "Street 45 and lisboa",
      "phone": "(2345)78690",
      "website": "https://creperiaelmediodiaec.com/",
      "image": "Creperia.webp",
      "membership_level": 3,
      "description": "The midday creperie offers a wide variety of sweets"
    },
    {
      "name": "hospital San juan",
      "address": "Road 45 and E-34",
      "phone": "(2365)78697",
      "website": "https://hospitalsanjuan.ec/",
      "image": "Hospital.webp",
      "membership_level": 2,
      "description": "San Juan Hospital, one of the private hospitals with extensive technology to offer to its clients"
    },
    {
      "name": "Hotel Zeus",
      "address": "Road 34 /23",
      "phone": "(2345)88690",
      "website": "https://hotelzeus.com.ec/",
      "image":"Hotelzeus.webp",
      "membership_level": 3,
      "description": "Locatel San Juan, one of the most expensive hotels in Ecuador"
    },
    {
      "name": "Sacha Textil",
      "address": "Street 45 and lisboa",
      "phone": "(234)7498690",
      "website": "https://sachatextil.com/",
      "image": "images.webp",
      "membership_level": 1,
      "description": "Sacha textile being one of the centers of textiles in would offer well import with more wide"
    },
    {
      "name": "Sausages La Iberica ",
      "address": "Ave 54 Street 15",
      "phone": "(2345)458690",
      "website": "https://www.laiberica.com/",
      "image": "iberica.webp",
      "membership_level": 1,
      "description": "The sausages in the Iberian region, known for their quality sausages, are from the city."
    },
    {
      "name": "La fortaleza steak and wine",
      "address": "Street 43 road 34",
      "phone": "(6445)78660",
      "website": "https://la-fortaleza-steak-wine.reservio.com/",
      "image": "Fotalezsteak.webp",
      "membership_level": 2,
      "description": "La Fortaleza meat and wine restaurant known for its excellent service"
    },
    {
      "name": "Automotres Continental",
      "address": "Road 34",
      "phone": "(2345)78670",
      "website": "https://www.automotorescontinental.com/",
      "image": "Continetal.webp",
      "membership_level": 3,
      "description": "Continental dealership one of the car dealerships that"
    }
  ]
}